{
  "ir_version": "9",
  "graph": {
    "node": [
      {
        "input": [
          "X"
        ],
        "output": [
          "Y"
        ],
        "name": "AvgPool_0",
        "op_type": "AveragePool",
        "attribute": [
          {
            "name": "ceil_mode",
            "i": "0",
            "type": "INT"
          },
          {
            "name": "count_include_pad",
            "i": "0",
            "type": "INT"
          },
          {
            "name": "kernel_shape",
            "ints": [
              "3",
              "3"
            ],
            "type": "INTS"
          },
          {
            "name": "pads",
            "ints": [
              "1",
              "1",
              "1",
              "1"
            ],
            "type": "INTS"
          },
          {
            "name": "strides",
            "ints": [
              "2",
              "2"
            ],
            "type": "INTS"
          }
        ]
      }
    ],
    "name": "avgpool_standard",
    "input": [
      {
        "name": "X",
        "type": {
          "tensor_type": {
            "elem_type": 1,
            "shape": {
              "dim": [
                {
                  "dim_value": "1"
                },
                {
                  "dim_value": "2"
                },
                {
                  "dim_value": "5"
                },
                {
                  "dim_value": "6"
                }
              ]
            }
          }
        }
      }
    ],
    "output": [
      {
        "name": "Y",
        "type": {
          "tensor_type": {
            "elem_type": 1,
            "shape": {
              "dim": [
                {
                  "dim_value": "1"
                },
                {
                  "dim_value": "2"
                },
                {
                  "dim_value": "3"
                },
                {
                  "dim_value": "3"
                }
              ]
            }
          }
        }
      }
    ]
  },
  "opset_import": [
    {
      "domain": "",
      "version": "13"
    }
  ]
}